{"trial_id": "06", "hyperparameters": {"space": [{"class_name": "Choice", "config": {"name": "activation", "default": "LeakyReLU", "conditions": [], "values": ["LeakyReLU", "gelu", "relu"], "ordered": false}}, {"class_name": "Int", "config": {"name": "layer_1", "default": null, "conditions": [], "min_value": 0, "max_value": 512, "step": 16, "sampling": "linear"}}, {"class_name": "Int", "config": {"name": "layer_2", "default": null, "conditions": [], "min_value": 0, "max_value": 512, "step": 16, "sampling": "linear"}}, {"class_name": "Choice", "config": {"name": "learning_rate", "default": 0.01, "conditions": [], "values": [0.01, 0.001, 0.0001, 5e-05], "ordered": true}}], "values": {"activation": "gelu", "layer_1": 224, "layer_2": 368, "learning_rate": 5e-05}}, "metrics": {"metrics": {"loss": {"direction": "min", "observations": [{"value": [0.6912918090820312], "step": 48}]}, "accuracy": {"direction": "max", "observations": [{"value": [0.850649356842041], "step": 48}]}, "val_loss": {"direction": "min", "observations": [{"value": [0.9192708730697632], "step": 48}]}, "val_accuracy": {"direction": "max", "observations": [{"value": [0.7806451320648193], "step": 48}]}}}, "score": 0.7806451320648193, "best_step": 48, "status": "COMPLETED", "message": null}